msc/__init__.py
msc/adbcap.py
msc_adb-0.0.1.dist-info/METADATA
msc_adb-0.0.1.dist-info/WHEEL
msc_adb-0.0.1.dist-info/top_level.txt
msc_adb-0.0.1.dist-info/RECORD
