Metadata-Version: 2.1
Name: msc-adb
Version: 0.0.1
Summary: 截图工具-adb
Author: KateTseng
Author-email: Kate.TsengK@outlook.com
License: MIT
Keywords: Auto Script Testing
Requires-Python: >=3
Requires-Dist: opencv-python
Requires-Dist: adbutils
Requires-Dist: msc-base
